{"title": "C# Performance Tips", "content": "<h3>Check List has items <strong>List.Count() vs List.Any()</strong></h3>\n<pre><code data-enlighter-language=\"null\">Stopwatch watch = new Stopwatch();  \r\nList &lt; string &gt; strs = new List &lt; string &gt; () {  \r\n    \"Akshay\",  \r\n    \"Patel\",  \r\n    \"Panth\",  \r\n    \"Patel\"  \r\n};  \r\nwatch.Start();  \r\nif (strs.Count() &gt; 0) {}  \r\nConsole.WriteLine(\"List.Count()-{0}\", watch.Elapsed);\r\n\r\n--------\r\n\r\nwatch.Restart();  \r\nif (strs.Any()) {}  \r\nConsole.WriteLine(\"List.Any() - {0}\", watch.Elapsed);</code></pre>\n<p><img class=\"alignnone size-full wp-image-1311\" src=\"https://emolike.net/wp-content/uploads/2019/05/41.png\" width=\"904\" height=\"341\" alt=\"List.Count() Vs List.Any()\" srcset=\"https://emolike.net/wp-content/uploads/2019/05/41.png 904w, https://emolike.net/wp-content/uploads/2019/05/41-300x113.png 300w, https://emolike.net/wp-content/uploads/2019/05/41-768x290.png 768w\" sizes=\"(max-width: 904px) 100vw, 904px\" /></p>\n<p> </p>\n<h3>Loop on items in a list <strong>Array.Length vs var i = Array.Length</strong></h3>\n<pre><code data-enlighter-language=\"null\">Stopwatch watch = new Stopwatch();  \r\nwatch.Start();  \r\nstring[] names = {  \r\n    \"Akshay\",  \r\n    \"Patel\",  \r\n    \"Panth\"  \r\n};  \r\nfor (int i = 0; i &lt; names.Length; i++) {}  \r\nConsole.WriteLine(\"Name.Length Direct-{0}\", watch.Elapsed); \r\n\r\n---------\r\n\r\nwatch.Restart();  \r\nstring[] names1 = {  \r\n    \"Akshay\",  \r\n    \"Patel\",  \r\n    \"Panth\"  \r\n};  \r\nint k = names1.Length;  \r\nfor (int j = 0; j &lt; k; j++) {}  \r\nConsole.WriteLine(\"Name.Length Parameter-{0}\", watch.Elapsed);</code></pre>\n<p><img class=\"alignnone size-full wp-image-1312\" src=\"https://emolike.net/wp-content/uploads/2019/05/61.png\" width=\"1024\" height=\"381\" alt=\"Array Length\" srcset=\"https://emolike.net/wp-content/uploads/2019/05/61.png 1024w, https://emolike.net/wp-content/uploads/2019/05/61-300x112.png 300w, https://emolike.net/wp-content/uploads/2019/05/61-768x286.png 768w\" sizes=\"(max-width: 1024px) 100vw, 1024px\" /></p>\n<h3>String split Char vs Char[]</h3>\n<pre><code data-enlighter-language=\"null\">string str = \"Akshay|Patel\";  \r\nStopwatch s1 = new Stopwatch();  \r\ns1.Start();  \r\nstring[] temp1 = str.Split('|');  \r\nConsole.WriteLine(s1.ElapsedTicks.ToString()); \r\n\r\n------------------\r\n\r\nStopwatch s2 = new Stopwatch();  \r\ns2.Start();  \r\nstring[] temp = str.Split(new char[] {  \r\n    '|'  \r\n});  \r\nConsole.WriteLine(s2.ElapsedTicks.ToString());  \r\n</code></pre>\n<p><img class=\"alignnone size-full wp-image-1313\" src=\"https://emolike.net/wp-content/uploads/2019/05/12.png\" width=\"643\" height=\"314\" alt=\"C# Programming Performance\" srcset=\"https://emolike.net/wp-content/uploads/2019/05/12.png 643w, https://emolike.net/wp-content/uploads/2019/05/12-300x147.png 300w\" sizes=\"(max-width: 643px) 100vw, 643px\" /></p>\n<h3>Count of items in a list List.Count() vs List.Count</h3>\n<pre><code data-enlighter-language=\"null\">watch.Start();  \r\nint count = strs.Count();  \r\nConsole.WriteLine(\"Count()-{0}\", watch.Elapsed);  \r\n\r\n----\r\nwatch.Restart();  \r\nint count1 = strs.Count;  \r\nConsole.WriteLine(\"Count - {0}\", watch.Elapsed);</code></pre>\n<p><img class=\"alignnone size-full wp-image-1314\" src=\"https://emolike.net/wp-content/uploads/2019/05/51.png\" width=\"767\" height=\"344\" alt=\"List.Count() vs List.Count\" srcset=\"https://emolike.net/wp-content/uploads/2019/05/51.png 767w, https://emolike.net/wp-content/uploads/2019/05/51-300x135.png 300w\" sizes=\"(max-width: 767px) 100vw, 767px\" /></p>\n<p>Source : <a href=\"https://www.c-sharpcorner.com/blogs/c-sharp-programming-performance-tips-part-one-string-split\">https://www.c-sharpcorner.com/blogs/c-sharp-programming-performance-tips-part-one-string-split</a></p>\n", "slug": "c-performance-tips", "date": 1558017457, "cats": [0, 13, 14]}